bolt_selectors/__init__.py
bolt_selectors/parse.py
bolt_selectors/plugin.py
bolt_selectors/selector.py
bolt_selectors/types.py
bolt_selectors-0.4.0.dist-info/WHEEL
bolt_selectors-0.4.0.dist-info/METADATA
bolt_selectors-0.4.0.dist-info/RECORD
